flatten/flatten.py
flatten/__init__.py
flatten/tests/test_flatten.py
flatten/tests/__init__.py
FlattenList-0.1.4.dist-info/DESCRIPTION.rst
FlattenList-0.1.4.dist-info/METADATA
FlattenList-0.1.4.dist-info/metadata.json
FlattenList-0.1.4.dist-info/RECORD
FlattenList-0.1.4.dist-info/top_level.txt
FlattenList-0.1.4.dist-info/WHEEL
