Metadata-Version: 2.0
Name: FlattenList
Version: 0.1.4
Summary: Given a list of nested lists/tuples, returns all the elements in a single list
Home-page: https://pypi.python.org/pypi/FlattenList
Author: Akul Mathur
Author-email: akurnya@gmail.com
License: UNKNOWN
Platform: UNKNOWN
Classifier: Development Status :: 3 - Alpha
Classifier: Programming Language :: Python :: 2.7
Classifier: Topic :: Utilities
Classifier: Natural Language :: English
Classifier: License :: Freely Distributable
